mlrank/__init__.py
mlrank/mlrank.py
mlrank-0.0.1a4.dist-info/DESCRIPTION.rst
mlrank-0.0.1a4.dist-info/METADATA
mlrank-0.0.1a4.dist-info/RECORD
mlrank-0.0.1a4.dist-info/WHEEL
mlrank-0.0.1a4.dist-info/metadata.json
mlrank-0.0.1a4.dist-info/top_level.txt
